ssai/__init__.py
ssai/ssai.py
ssai-1.0.10.dist-info/LICENSE
ssai-1.0.10.dist-info/METADATA
ssai-1.0.10.dist-info/WHEEL
ssai-1.0.10.dist-info/entry_points.txt
ssai-1.0.10.dist-info/top_level.txt
ssai-1.0.10.dist-info/RECORD
