Metadata-Version: 2.1
Name: ssai
Version: 1.0.10
Summary: SuperSummarizeAI is a versatile Python tool designed to extract and summarize textual content. Whether it's from a provided webpage URL, a YouTube video link, or a PDF file, this tool processes the content through ChatGPT to generate an insightful summary.
Home-page: https://github.com/alexandrevl/SuperSummarizeAI
Author: Alexandre Lima
Author-email: alexandrevl@gmail.com
Classifier: Development Status :: 3 - Alpha
Classifier: Intended Audience :: Developers
Classifier: License :: OSI Approved :: MIT License
Classifier: Programming Language :: Python :: 3.6
Classifier: Programming Language :: Python :: 3.7
Classifier: Programming Language :: Python :: 3.8
Classifier: Programming Language :: Python :: 3.9
License-File: LICENSE
Requires-Dist: requests
Requires-Dist: beautifulsoup4
Requires-Dist: pyperclip
Requires-Dist: urllib3
Requires-Dist: PyPDF2
Requires-Dist: openai
Requires-Dist: python-dotenv
Requires-Dist: youtube-transcript-api
